[
  {"contractor":{"name":"Nandi Civic Infra Pvt Ltd","registration_no":"KA-2023-1001"},"asset":{"type":"road","lat":12.9716,"lng":77.5946,"ward_id":"ward_42"},"contract":{"contract_number":"BLR-PWD-2024-0001","contract_value_inr":4200000,"completion_date":"2024-08-15","warranty_months":24,"is_synthetic":true}},
  {"contractor":{"name":"Kaveri Urban Works LLP","registration_no":"KA-2022-1002"},"asset":{"type":"drain","lat":12.9758,"lng":77.6050,"ward_id":"ward_43"},"contract":{"contract_number":"BLR-PWD-2024-0002","contract_value_inr":3100000,"completion_date":"2024-11-10","warranty_months":24,"is_synthetic":true}},
  {"contractor":{"name":"MetroWard Services Ltd","registration_no":"KA-2021-1003"},"asset":{"type":"water_pipe","lat":12.9352,"lng":77.6245,"ward_id":"ward_67"},"contract":{"contract_number":"BLR-PWD-2025-0003","contract_value_inr":5600000,"completion_date":"2025-01-20","warranty_months":24,"is_synthetic":true}},
  {"contractor":{"name":"Nandi Civic Infra Pvt Ltd","registration_no":"KA-2023-1001"},"asset":{"type":"street_light","lat":13.0358,"lng":77.5970,"ward_id":"ward_21"},"contract":{"contract_number":"BLR-PWD-2025-0004","contract_value_inr":1800000,"completion_date":"2025-03-01","warranty_months":24,"is_synthetic":true}},
  {"contractor":{"name":"Kaveri Urban Works LLP","registration_no":"KA-2022-1002"},"asset":{"type":"road","lat":12.9141,"lng":77.6101,"ward_id":"ward_88"},"contract":{"contract_number":"BLR-PWD-2025-0005","contract_value_inr":7300000,"completion_date":"2025-06-12","warranty_months":24,"is_synthetic":true}},
  {"contractor":{"name":"MetroWard Services Ltd","registration_no":"KA-2021-1003"},"asset":{"type":"drain","lat":12.9982,"lng":77.5530,"ward_id":"ward_12"},"contract":{"contract_number":"BLR-PWD-2025-0006","contract_value_inr":2900000,"completion_date":"2025-08-21","warranty_months":24,"is_synthetic":true}},
  {"contractor":{"name":"Nandi Civic Infra Pvt Ltd","registration_no":"KA-2023-1001"},"asset":{"type":"water_pipe","lat":12.9698,"lng":77.7499,"ward_id":"ward_54"},"contract":{"contract_number":"BLR-PWD-2025-0007","contract_value_inr":6400000,"completion_date":"2025-09-30","warranty_months":24,"is_synthetic":true}},
  {"contractor":{"name":"Kaveri Urban Works LLP","registration_no":"KA-2022-1002"},"asset":{"type":"road","lat":12.8452,"lng":77.6602,"ward_id":"ward_99"},"contract":{"contract_number":"BLR-PWD-2026-0008","contract_value_inr":8100000,"completion_date":"2026-01-15","warranty_months":24,"is_synthetic":true}},
  {"contractor":{"name":"MetroWard Services Ltd","registration_no":"KA-2021-1003"},"asset":{"type":"road","lat":12.9279,"lng":77.6271,"ward_id":"ward_68"},"contract":{"contract_number":"BLR-PWD-2021-0009","contract_value_inr":3900000,"completion_date":"2021-07-10","warranty_months":24,"is_synthetic":true}},
  {"contractor":{"name":"Nandi Civic Infra Pvt Ltd","registration_no":"KA-2023-1001"},"asset":{"type":"drain","lat":13.0098,"lng":77.5511,"ward_id":"ward_11"},"contract":{"contract_number":"BLR-PWD-2022-0010","contract_value_inr":2600000,"completion_date":"2022-03-05","warranty_months":24,"is_synthetic":true}},
  {"contractor":{"name":"Kaveri Urban Works LLP","registration_no":"KA-2022-1002"},"asset":{"type":"street_light","lat":12.9569,"lng":77.7011,"ward_id":"ward_57"},"contract":{"contract_number":"BLR-PWD-2022-0011","contract_value_inr":1200000,"completion_date":"2022-09-16","warranty_months":24,"is_synthetic":true}},
  {"contractor":{"name":"MetroWard Services Ltd","registration_no":"KA-2021-1003"},"asset":{"type":"water_pipe","lat":13.0235,"lng":77.6408,"ward_id":"ward_30"},"contract":{"contract_number":"BLR-PWD-2023-0012","contract_value_inr":4800000,"completion_date":"2023-01-25","warranty_months":24,"is_synthetic":true}},
  {"contractor":{"name":"Nandi Civic Infra Pvt Ltd","registration_no":"KA-2023-1001"},"asset":{"type":"road","lat":12.9081,"lng":77.6476,"ward_id":"ward_94"},"contract":{"contract_number":"BLR-PWD-2023-0013","contract_value_inr":5900000,"completion_date":"2023-02-17","warranty_months":24,"is_synthetic":true}},
  {"contractor":{"name":"Kaveri Urban Works LLP","registration_no":"KA-2022-1002"},"asset":{"type":"drain","lat":12.9872,"lng":77.5128,"ward_id":"ward_08"},"contract":{"contract_number":"BLR-PWD-2023-0014","contract_value_inr":3300000,"completion_date":"2023-04-02","warranty_months":24,"is_synthetic":true}},
  {"contractor":{"name":"MetroWard Services Ltd","registration_no":"KA-2021-1003"},"asset":{"type":"street_light","lat":12.9611,"lng":77.6387,"ward_id":"ward_72"},"contract":{"contract_number":"BLR-PWD-2024-0015","contract_value_inr":1600000,"completion_date":"2024-05-05","warranty_months":24,"is_synthetic":true}},
  {"contractor":{"name":"Nandi Civic Infra Pvt Ltd","registration_no":"KA-2023-1001"},"asset":{"type":"road","lat":13.0012,"lng":77.6180,"ward_id":"ward_32"},"contract":{"contract_number":"BLR-PWD-2024-0016","contract_value_inr":6800000,"completion_date":"2024-06-20","warranty_months":24,"is_synthetic":true}},
  {"contractor":{"name":"Kaveri Urban Works LLP","registration_no":"KA-2022-1002"},"asset":{"type":"water_pipe","lat":12.9369,"lng":77.5172,"ward_id":"ward_04"},"contract":{"contract_number":"BLR-PWD-2024-0017","contract_value_inr":5200000,"completion_date":"2024-07-01","warranty_months":24,"is_synthetic":true}},
  {"contractor":{"name":"MetroWard Services Ltd","registration_no":"KA-2021-1003"},"asset":{"type":"drain","lat":12.8996,"lng":77.5853,"ward_id":"ward_90"},"contract":{"contract_number":"BLR-PWD-2024-0018","contract_value_inr":3500000,"completion_date":"2024-09-12","warranty_months":24,"is_synthetic":true}},
  {"contractor":{"name":"Nandi Civic Infra Pvt Ltd","registration_no":"KA-2023-1001"},"asset":{"type":"street_light","lat":13.0623,"lng":77.5871,"ward_id":"ward_18"},"contract":{"contract_number":"BLR-PWD-2024-0019","contract_value_inr":1400000,"completion_date":"2024-10-08","warranty_months":24,"is_synthetic":true}},
  {"contractor":{"name":"Kaveri Urban Works LLP","registration_no":"KA-2022-1002"},"asset":{"type":"road","lat":12.9784,"lng":77.6408,"ward_id":"ward_50"},"contract":{"contract_number":"BLR-PWD-2024-0020","contract_value_inr":7600000,"completion_date":"2024-12-20","warranty_months":24,"is_synthetic":true}}
]
